{
  "_doc": "Per-package main-entry budgets in BYTES (minified + gzipped). Externalizes @pyreon/*, node:*, and every bare-module import auto-collected from each package's lib/ tree — this is the unique code each package adds to a consumer bundle. Set at 25% headroom over current size at PR-time. When a package legitimately needs to grow past its budget, bump the value in the same PR for explicit review.",
  "_units": "bytes (gzipped)",
  "@pyreon/a11y": 1024,
  "@pyreon/attrs": 1280,
  "@pyreon/charts": 256,
  "@pyreon/cli": 13312,
  "@pyreon/code": 7168,
  "@pyreon/compiler": 45056,
  "@pyreon/connector-document": 2304,
  "@pyreon/coolgrid": 2304,
  "@pyreon/core": 5888,
  "@pyreon/create-multiplatform": 8500,
  "@pyreon/create-zero": 10240,
  "@pyreon/dnd": 3328,
  "@pyreon/document": 2816,
  "@pyreon/document-primitives": 2816,
  "@pyreon/elements": 8448,
  "@pyreon/feature": 3584,
  "@pyreon/flow": 15616,
  "@pyreon/form": 4608,
  "@pyreon/head": 256,
  "@pyreon/hooks": 4608,
  "@pyreon/hotkeys": 2304,
  "@pyreon/i18n": 3584,
  "@pyreon/kinetic": 4864,
  "@pyreon/kinetic-presets": 4864,
  "@pyreon/lint": 512,
  "@pyreon/machine": 1150,
  "@pyreon/mcp": 186112,
  "@pyreon/meta": 1536,
  "@pyreon/permissions": 1024,
  "@pyreon/preact-compat": 1280,
  "@pyreon/primitives": 4096,
  "@pyreon/query": 3840,
  "@pyreon/react-compat": 3584,
  "@pyreon/reactivity": 9216,
  "@pyreon/rocketstyle": 5120,
  "@pyreon/router": 12288,
  "@pyreon/runtime-dom": 12544,
  "@pyreon/runtime-server": 6144,
  "@pyreon/rx": 2304,
  "@pyreon/server": 3328,
  "@pyreon/sized-map": 512,
  "@pyreon/solid-compat": 4864,
  "@pyreon/state-tree": 3840,
  "@pyreon/storage": 3072,
  "@pyreon/store": 3072,
  "@pyreon/storybook": 256,
  "@pyreon/styler": 7168,
  "@pyreon/svelte-compat": 2816,
  "@pyreon/sync": 1792,
  "@pyreon/table": 768,
  "@pyreon/toast": 3072,
  "@pyreon/ui-core": 3584,
  "@pyreon/unistyle": 9472,
  "@pyreon/url-state": 1536,
  "@pyreon/validate": 12288,
  "@pyreon/validation": 1792,
  "@pyreon/virtual": 1024,
  "@pyreon/vite-plugin": 11264,
  "@pyreon/vue-compat": 4864,
  "@pyreon/zero": 8704,
  "@pyreon/zero-cli": 3072,
  "@pyreon/zero-content": 11428
}
