{
  "_doc": "Per-package main-entry budgets in BYTES (minified + gzipped). Externalizes @pyreon/*, node:*, @tanstack/*, echarts, elkjs, codemirror — this is the unique code each package adds to a consumer bundle. Set at 25% headroom over current size at PR-time. When a package legitimately needs to grow past its budget, bump the value in the same PR for explicit review.",
  "_units": "bytes (gzipped)",
  "@pyreon/attrs": 1280,
  "@pyreon/charts": 2560,
  "@pyreon/cli": 2816,
  "@pyreon/code": 7424,
  "@pyreon/connector-document": 2304,
  "@pyreon/coolgrid": 2560,
  "@pyreon/core": 4352,
  "@pyreon/create-zero": 32256,
  "@pyreon/dnd": 15872,
  "@pyreon/document-primitives": 2816,
  "@pyreon/elements": 8192,
  "@pyreon/feature": 3584,
  "@pyreon/flow": 16128,
  "@pyreon/form": 4096,
  "@pyreon/head": 2048,
  "@pyreon/hooks": 4608,
  "@pyreon/hotkeys": 1792,
  "@pyreon/i18n": 2560,
  "@pyreon/kinetic": 4864,
  "@pyreon/kinetic-presets": 4864,
  "@pyreon/machine": 768,
  "@pyreon/meta": 2304,
  "@pyreon/permissions": 1024,
  "@pyreon/preact-compat": 1280,
  "@pyreon/query": 3584,
  "@pyreon/react-compat": 3584,
  "@pyreon/reactivity": 5120,
  "@pyreon/rocketstyle": 5376,
  "@pyreon/router": 10752,
  "@pyreon/runtime-dom": 15104,
  "@pyreon/runtime-server": 3584,
  "@pyreon/rx": 2304,
  "@pyreon/server": 3840,
  "@pyreon/solid-compat": 4096,
  "@pyreon/state-tree": 2048,
  "@pyreon/storage": 3328,
  "@pyreon/store": 1536,
  "@pyreon/storybook": 768,
  "@pyreon/styler": 6144,
  "@pyreon/table": 768,
  "@pyreon/toast": 3072,
  "@pyreon/ui-core": 3328,
  "@pyreon/unistyle": 8192,
  "@pyreon/url-state": 1536,
  "@pyreon/validation": 768,
  "@pyreon/virtual": 1024,
  "@pyreon/vite-plugin": 4608,
  "@pyreon/vue-compat": 3840,
  "@pyreon/zero": 6656
}
